python_asip_client/__init__.py
python_asip_client/mirto_robot.py
python_asip_client/mqtt_mirto_robot.py
python_asip_client/serial_mirto_robot.py
python_asip_client/tcp_mirto_robot.py
python_asip_client/tcp_serial_bridge.py
python_asip_client/boards/__init__.py
python_asip_client/boards/asip_client.py
python_asip_client/boards/asip_writer.py
python_asip_client/boards/kbhit.py
python_asip_client/boards/mqtt_board.py
python_asip_client/boards/old_mqtt_board.py
python_asip_client/boards/old_serial_board.py
python_asip_client/boards/old_tcp_board.py
python_asip_client/boards/port_manager.py
python_asip_client/boards/serial_board.py
python_asip_client/boards/tcp_board.py
python_asip_client/examples/LightSwitch.py
python_asip_client/examples/LightSwitchMQTT.py
python_asip_client/examples/LightSwitchTCP.py
python_asip_client/examples/Potentiometer.py
python_asip_client/examples/PotentiometerMQTT.py
python_asip_client/examples/PotentiometerTCP.py
python_asip_client/examples/SimpleBlink.py
python_asip_client/examples/SimpleMQTTBlink.py
python_asip_client/examples/SimpleTCPBlink.py
python_asip_client/examples/__init__.py
python_asip_client/examples/example_apps/SimpleMQTTWeatherStation.py
python_asip_client/examples/example_apps/SimpleWeatherStation.py
python_asip_client/examples/example_apps/TwoBoardSwitchMQTT.py
python_asip_client/examples/example_apps/__init__.py
python_asip_client/examples/example_apps/mqtt_mirto_pid_follower.py
python_asip_client/services/__init__.py
python_asip_client/services/asip_service.py
python_asip_client/services/bump_service.py
python_asip_client/services/distance_service.py
python_asip_client/services/encoder_service.py
python_asip_client/services/ir_service.py
python_asip_client/services/lcd_service.py
python_asip_client/services/motor_service.py
python_asip_client/services/neopixel_service.py
python_asip_client/services/servo_service.py
python_asip_client/services/sparkfunws_service.py
python_asip_client-1.0.9.dist-info/METADATA
python_asip_client-1.0.9.dist-info/RECORD
python_asip_client-1.0.9.dist-info/WHEEL
python_asip_client-1.0.9.dist-info/top_level.txt
