Metadata-Version: 2.1
Name: python-asip-client
Version: 1.0.9
Summary: Serial manager for Mirto robot services
Home-page: https://github.com/mdxmase/python-asip
Author: Gianluca Barbon, Adam Jarzebak, Michael Margolis, Franco Raimondi, Timbo Cole, Daniel Ionita
Author-email: adam@jarzebak.eu
License: UNKNOWN
Platform: UNKNOWN
Classifier: Programming Language :: Python :: 3
Classifier: License :: OSI Approved :: MIT License
Classifier: Operating System :: OS Independent
